Workbook

Sheet 1_Mortality_Table
A1: CSO 1980 MORTALITY TABLE
A2: Source: Circular 156/2007/TT-BTC (Dec 20, 2007) by the Ministry of Finance (MOF) | Scope: Ages 25–50 (aligned with 15-year Endowment)
A4: Age (x) | B4: qx Male | C4: px Male (1-qx) | D4: lx Male (survivors) | E4: dx Male (deaths) | F4: qx Female | G4: px Female (1-qx) | H4: lx Female (survivors) | I4: dx Female (deaths)
A5: 25 | B5: 0.00175 | C5: =1-B5 -> 0.99825 | D5: 100000 | E5: =D5*B5 -> 175 | F5: 0.00117 | G5: =1-F5 -> 0.99883 | H5: 100000 | I5: =H5*F5 -> 117
A6: 26 | B6: 0.00172 | C6: =1-B6 -> 0.99828 | D6: =D5*C5 -> 99825 | E6: =D6*B6 -> 171.699 | F6: 0.0012 | G6: =1-F6 -> 0.9988 | H6: =H5*G5 -> 99883 | I6: =H6*F6 -> 119.8596
A7: 27 | B7: 0.00171 | C7: =1-B7 -> 0.99829 | D7: =D6*C6 -> 99653.301 | E7: =D7*B7 -> 170.40714 | F7: 0.00124 | G7: =1-F7 -> 0.99876 | H7: =H6*G6 -> 99763.14 | I7: =H7*F7 -> 123.70629
A8: 28 | B8: 0.0017 | C8: =1-B8 -> 0.9983 | D8: =D7*C7 -> 99482.894 | E8: =D8*B8 -> 169.12092 | F8: 0.00128 | G8: =1-F8 -> 0.99872 | H8: =H7*G7 -> 99639.434 | I8: =H8*F8 -> 127.53848
A9: 29 | B9: 0.00172 | C9: =1-B9 -> 0.99828 | D9: =D8*C8 -> 99313.773 | E9: =D9*B9 -> 170.81969 | F9: 0.00132 | G9: =1-F9 -> 0.99868 | H9: =H8*G8 -> 99511.896 | I9: =H9*F9 -> 131.3557
A10: 30 | B10: 0.00175 | C10: =1-B10 -> 0.99825 | D10: =D9*C9 -> 99142.953 | E10: =D10*B10 -> 173.50017 | F10: 0.00137 | G10: =1-F10 -> 0.99863 | H10: =H9*G9 -> 99380.54 | I10: =H10*F10 -> 136.15134
A11: 31 | B11: 0.0018 | C11: =1-B11 -> 0.9982 | D11: =D10*C10 -> 98969.453 | E11: =D11*B11 -> 178.14502 | F11: 0.00142 | G11: =1-F11 -> 0.99858 | H11: =H10*G10 -> 99244.389 | I11: =H11*F11 -> 140.92703
A12: 32 | B12: 0.00187 | C12: =1-B12 -> 0.99813 | D12: =D11*C11 -> 98791.308 | E12: =D12*B12 -> 184.73975 | F12: 0.00147 | G12: =1-F12 -> 0.99853 | H12: =H11*G11 -> 99103.462 | I12: =H12*F12 -> 145.68209
A13: 33 | B13: 0.00195 | C13: =1-B13 -> 0.99805 | D13: =D12*C12 -> 98606.568 | E13: =D13*B13 -> 192.28281 | F13: 0.00154 | G13: =1-F13 -> 0.99846 | H13: =H12*G12 -> 98957.779 | I13: =H13*F13 -> 152.39498
A14: 34 | B14: 0.00205 | C14: =1-B14 -> 0.99795 | D14: =D13*C13 -> 98414.286 | E14: =D14*B14 -> 201.74929 | F14: 0.00161 | G14: =1-F14 -> 0.99839 | H14: =H13*G13 -> 98805.384 | I14: =H14*F14 -> 159.07667
A15: 35 | B15: 0.00217 | C15: =1-B15 -> 0.99783 | D15: =D14*C14 -> 98212.536 | E15: =D15*B15 -> 213.1212 | F15: 0.0017 | G15: =1-F15 -> 0.9983 | H15: =H14*G14 -> 98646.308 | I15: =H15*F15 -> 167.69872
A16: 36 | B16: 0.00232 | C16: =1-B16 -> 0.99768 | D16: =D15*C15 -> 97999.415 | E16: =D16*B16 -> 227.35864 | F16: 0.00182 | G16: =1-F16 -> 0.99818 | H16: =H15*G15 -> 98478.609 | I16: =H16*F16 -> 179.23107
A17: 37 | B17: 0.00249 | C17: =1-B17 -> 0.99751 | D17: =D16*C16 -> 97772.056 | E17: =D17*B17 -> 243.45242 | F17: 0.00196 | G17: =1-F17 -> 0.99804 | H17: =H16*G16 -> 98299.378 | I17: =H17*F17 -> 192.66678
... A30: 50 | B30: 0.007 | C30: =1-B30 -> 0.993 | D30: =D29*C29 -> 92568.96 | E30: =D30*B30 -> 647.98272 | F30: 0.00513 | G30: =1-F30 -> 0.99487 | H30: =H29*G29 -> 94214.438 | I30: =H30*F30 -> 483.32007
A32: Note: Initial lx = 100,000 (radix). px = probability of survival. dx = number of deaths. Male table utilized for Base Case pricing.

Sheet 2_Pricing_Engine
A1: PRICING ENGINE — EDUCATION ENDOWMENT INSURANCE
A2: Lapse-Adjusted Net Premium Calculation | CSO 1980 Mortality | Vietnam Market
A4: KEY ASSUMPTIONS (Yellow cells = Dynamic Inputs / Automatically recalculate the model)
A5: Entry age (x) | B5: 30 | C5: year
A6: Policy Term (n) | B6: 15 | C6: year
A7: Sum Assured (S) | B7: 800000000 | C7: VND
A8: Technical Interest Rate (i) | B8: 0.05 | C8: 5.00%
A9: Lapse rate Year 1 | B9: 0.2 | C9: 20%
A10: Lapse rate year 2+ | B10: 0.08 | C10: 8%
A11: Mortality loading factor | B11: 1 | C11: 100% of CSO 1980
A13: YEAR-BY-YEAR PROJECTION TABLE
A14: Year (t) | B14: Age (x+t) | C14: qx (CSO1980) | D14: px | E14: tPx (survival) | F14: Lapse Survival | G14: vt (discount) | H14: tPx × vt | I14: Lapse-adj tPx × vt | J14: Reserve Vt (approx)
A15: 1 | B15: =$B$5+A15-1 -> 30 | C15: =INDEX('1_Mortality_Table'!$B$5:$B$30,MATCH(B15,'1_Mortality_Table'!$A$5:$A$30,0))*$B$11 -> 0.00175 | D15: =1-C15 -> 0.99825 | E15: =D15 -> 0.99825 | F15: =E15*(1-$B$9) -> 0.7986 | G15: =1/(1+$B$8)^A15 -> 0.95238095 | H15: =E15*G15 -> 0.95071429 | I15: =F15*G15 -> 0.76057143 | J15: → Sheet 3
A16: 2 | B16: =$B$5+A16-1 -> 31 | C16: =INDEX('1_Mortality_Table'!$B$5:$B$30,MATCH(B16,'1_Mortality_Table'!$A$5:$A$30,0))*$B$11 -> 0.0018 | D16: =1-C16 -> 0.9982 | E16: =E15*D16 -> 0.99645315 | F16: =F15*D16*(1-$B$10) -> 0.73338952 | G16: =1/(1+$B$8)^A16 -> 0.90702948 | H16: =E16*G16 -> 0.90381238 | I16: =F16*G16 -> 0.66520591 | J16: → Sheet 3
A17: 3 | B17: =$B$5+A17-1 -> 32 | C17: =INDEX('1_Mortality_Table'!$B$5:$B$30,MATCH(B17,'1_Mortality_Table'!$A$5:$A$30,0))*$B$11 -> 0.00187 | D17: =1-C17 -> 0.99813 | E17: =E16*D17 -> 0.99458978 | F17: =F16*D17*(1-$B$10) -> 0.67345663 | G17: =1/(1+$B$8)^A17 -> 0.8638376 | H17: =E17*G17 -> 0.85916405 | I17: =F17*G17 -> 0.58175716 | J17: → Sheet 3
A18: 4 | B18: =$B$5+A18-1 -> 33 | C18: =INDEX('1_Mortality_Table'!$B$5:$B$30,MATCH(B18,'1_Mortality_Table'!$A$5:$A$30,0))*$B$11 -> 0.00195 | D18: =1-C18 -> 0.99805 | E18: =E17*D18 -> 0.99265033 | F18: =F17*D18*(1-$B$10) -> 0.61837192 | G18: =1/(1+$B$8)^A18 -> 0.82270247 | H18: =E18*G18 -> 0.81665589 | I18: =F18*G18 -> 0.50873611 | J18: → Sheet 3
A19: 5 | B19: =$B$5+A19-1 -> 34 | C19: =INDEX('1_Mortality_Table'!$B$5:$B$30,MATCH(B19,'1_Mortality_Table'!$A$5:$A$30,0))*$B$11 -> 0.00205 | D19: =1-C19 -> 0.99795 | E19: =E18*D19 -> 0.9906154 | F19: =F18*D19*(1-$B$10) -> 0.56773592 | G19: =1/(1+$B$8)^A19 -> 0.78352617 | H19: =E19*G19 -> 0.77617309 | I19: =F19*G19 -> 0.44483595 | J19: → Sheet 3
A20: 6 | B20: =$B$5+A20-1 -> 35 | C20: =INDEX('1_Mortality_Table'!$B$5:$B$30,MATCH(B20,'1_Mortality_Table'!$A$5:$A$30,0))*$B$11 -> 0.00217 | D20: =1-C20 -> 0.99783 | E20: =E19*D20 -> 0.98846576 | F20: =F19*D20*(1-$B$10) -> 0.52118362 | G20: =1/(1+$B$8)^A20 -> 0.7462154 | H20: =E20*G20 -> 0.73760837 | I20: =F20*G20 -> 0.38891524 | J20: → Sheet 3
A21: 7 | B21: =$B$5+A21-1 -> 36 | C21: =INDEX('1_Mortality_Table'!$B$5:$B$30,MATCH(B21,'1_Mortality_Table'!$A$5:$A$30,0))*$B$11 -> 0.00232 | D21: =1-C21 -> 0.99768 | E21: =E20*D21 -> 0.98617252 | F21: =F20*D21*(1-$B$10) -> 0.47837651 | G21: =1/(1+$B$8)^A21 -> 0.71068133 | H21: =E21*G21 -> 0.7008544 | I21: =F21*G21 -> 0.33997326 | J21: → Sheet 3
A22: 8 | B22: =$B$5+A22-1 -> 37 | C22: =INDEX('1_Mortality_Table'!$B$5:$B$30,MATCH(B22,'1_Mortality_Table'!$A$5:$A$30,0))*$B$11 -> 0.00249 | D22: =1-C22 -> 0.99751 | E22: =E21*D22 -> 0.98371695 | F22: =F21*D22*(1-$B$10) -> 0.43901053 | G22: =1/(1+$B$8)^A22 -> 0.67683936 | H22: =E22*G22 -> 0.66581836 | I22: =F22*G22 -> 0.29713961 | J22: → Sheet 3
A23: 9 | B23: =$B$5+A23-1 -> 38 | C23: =INDEX('1_Mortality_Table'!$B$5:$B$30,MATCH(B23,'1_Mortality_Table'!$A$5:$A$30,0))*$B$11 -> 0.00268 | D23: =1-C23 -> 0.99732 | E23: =E22*D23 -> 0.98108059 | F23: =F22*D23*(1-$B$10) -> 0.40280726 | G23: =1/(1+$B$8)^A23 -> 0.64460892 | H23: =E23*G23 -> 0.6324133 | I23: =F23*G23 -> 0.25965315 | J23: → Sheet 3
A24: 10 | B24: =$B$5+A24-1 -> 39 | C24: =INDEX('1_Mortality_Table'!$B$5:$B$30,MATCH(B24,'1_Mortality_Table'!$A$5:$A$30,0))*$B$11 -> 0.0029 | D24: =1-C24 -> 0.9971 | E24: =E23*D24 -> 0.97823546 | F24: =F23*D24*(1-$B$10) -> 0.36950799 | G24: =1/(1+$B$8)^A24 -> 0.61391325 | H24: =E24*G24 -> 0.60055171 | I24: =F24*G24 -> 0.22684585 | J24: → Sheet 3
A25: 11 | B25: =$B$5+A25-1 -> 40 | C25: =INDEX('1_Mortality_Table'!$B$5:$B$30,MATCH(B25,'1_Mortality_Table'!$A$5:$A$30,0))*$B$11 -> 0.00315 | D25: =1-C25 -> 0.99685 | E25: =E24*D25 -> 0.97515402 | F25: =F24*D25*(1-$B$10) -> 0.33887652 | G25: =1/(1+$B$8)^A25 -> 0.58467929 | H25: =E25*G25 -> 0.57015236 | I25: =F25*G25 -> 0.19813408 | J25: → Sheet 3
A26: 12 | B26: =$B$5+A26-1 -> 41 | C26: =INDEX('1_Mortality_Table'!$B$5:$B$30,MATCH(B26,'1_Mortality_Table'!$A$5:$A$30,0))*$B$11 -> 0.00342 | D26: =1-C26 -> 0.99658 | E26: =E25*D26 -> 0.97181899 | F26: =F25*D26*(1-$B$10) -> 0.31070015 | G26: =1/(1+$B$8)^A26 -> 0.55683742 | H26: =E26*G26 -> 0.54114518 | I26: =F26*G26 -> 0.17300947 | J26: → Sheet 3
A27: 13 | B27: =$B$5+A27-1 -> 42 | C27: =INDEX('1_Mortality_Table'!$B$5:$B$30,MATCH(B27,'1_Mortality_Table'!$A$5:$A$30,0))*$B$11 -> 0.00371 | D27: =1-C27 -> 0.99629 | E27: =E26*D27 -> 0.96821354 | F27: =F26*D27*(1-$B$10) -> 0.28478366 | G27: =1/(1+$B$8)^A27 -> 0.53032135 | H27: =E27*G27 -> 0.51346431 | I27: =F27*G27 -> 0.15102686 | J27: → Sheet 3
... A29: 15 | B29: =$B$5+A29-1 -> 44 | C29: =INDEX('1_Mortality_Table'!$B$5:$B$30,MATCH(B29,'1_Mortality_Table'!$A$5:$A$30,0))*$B$11 -> 0.00437 | D29: =1-C29 -> 0.99563 | E29: =E28*D29 -> 0.9600976 | F29: =F28*D29*(1-$B$10) -> 0.23902039 | G29: =1/(1+$B$8)^A29 -> 0.4810171 | H29: =E29*G29 -> 0.46182336 | I29: =F29*G29 -> 0.1149729 | J29: → Sheet 3
A32: PRICING RESULTS
A33: Annuity Factor ä (no lapse) | B33: =SUM(H15:H29) -> 10.217394 | C33: VND factor
A34: Annuity Factor ä* (lapse-adjusted) | B34: =SUM(I15:I29) -> 5.242572 | C34: VND factor
A35: 15P15 — survival prob to maturity | B35: =E29 -> 0.9600976 | C35: probability
A36: Net Single Premium (NSP) | B36: =$B$7*E29*G29 -> 3.6945869e+08 | C36: VND
A37: Net Annual Premium — Base (NAP) | B37: 36284823 | C37: VND/year | D37: Premium calibrated via Python DCF (Goal Seek equivalent) to converge Year-15 Reserve to exactly 800M VND.
A38: NAP — Lapse Adjusted (NAP*) | B38: =B36/B34 -> 70472793 | C38: VND/year
A39: Premium Burden (% income 300M/yr) | B39: =B38/300000000 -> 0.23490931 | C39: %

Sheet 3_Reserve_Projection
A1: PROSPECTIVE RESERVE PROJECTION — 15-YEAR ENDOWMENT
A2: Vt = [ (Vt-1 + Premium) × (1+i) - Death Benefit × qx ] / px | Fackler's Retrospective Method
A4: RESERVE RUN-OFF TABLE (Base Scenario)
A5: Năm (t) | B5: Tuổi | C5: tPx | D5: PV Future Benefits | E5: PV Future Premiums | F5: Reserve Vt | G5: Reserve (% of Benefit)
A6: 0 | B6: ='2_Pricing_Engine'!$B$5+0 -> 30 | C6: — | D6: — | E6: — | F6: 0 | G6: 0.0%
A7: 1 | B7: ='2_Pricing_Engine'!$B$5+1 -> 31 | C7: ='2_Pricing_Engine'!E15 -> 0.99825 | D7: ='2_Pricing_Engine'!$B$7*('2_Pricing_Engine'!E29/'2_Pricing_Engine'!E15)*(1+'2_Pricing_Engine'!$B$8)^(-14) -> 3.8861169e+08 | E7: ='2_Pricing_Engine'!$B$37*('2_Pricing_Engine'!$B$32-SUM('2_Pricing_Engine'!H15:H15))/'2_Pricing_Engine'!E15 -> -34556974 | F7: =((F6+'2_Pricing_Engine'!$B$37)*1.05-800000000*'1_Mortality_Table'!B10)/'1_Mortality_Table'!C10 -> 36763400 | G7: =F7/'2_Pricing_Engine'!$B$7 -> 0.04595425
A8: 2 | B8: ='2_Pricing_Engine'!$B$5+2 -> 32 | C8: ='2_Pricing_Engine'!E16 -> 0.99645315 | D8: ='2_Pricing_Engine'!$B$7*('2_Pricing_Engine'!E29/'2_Pricing_Engine'!E16)*(1+'2_Pricing_Engine'!$B$8)^(-13) -> 4.0877808e+08 | E8: ='2_Pricing_Engine'!$B$37*('2_Pricing_Engine'!$B$32-SUM('2_Pricing_Engine'!H15:H16))/'2_Pricing_Engine'!E16 -> -67530693 | F8: =((F7+'2_Pricing_Engine'!$B$37)*1.05-800000000*'1_Mortality_Table'!B11)/'1_Mortality_Table'!C11 -> 75396348 | G8: =F8/'2_Pricing_Engine'!$B$7 -> 0.094245435
A9: 3 | B9: ='2_Pricing_Engine'!$B$5+3 -> 33 | C9: ='2_Pricing_Engine'!E17 -> 0.99458978 | D9: ='2_Pricing_Engine'!$B$7*('2_Pricing_Engine'!E29/'2_Pricing_Engine'!E17)*(1+'2_Pricing_Engine'!$B$8)^(-12) -> 4.3002112e+08 | E9: ='2_Pricing_Engine'!$B$37*('2_Pricing_Engine'!$B$32-SUM('2_Pricing_Engine'!H15:H17))/'2_Pricing_Engine'!E17 -> -99001406 | F9: =((F8+'2_Pricing_Engine'!$B$37)*1.05-800000000*'1_Mortality_Table'!B12)/'1_Mortality_Table'!C12 -> 1.1598612e+08 | G9: =F9/'2_Pricing_Engine'!$B$7 -> 0.14498265
A10: 4 | B10: ='2_Pricing_Engine'!$B$5+4 -> 34 | C10: ='2_Pricing_Engine'!E18 -> 0.99265033 | D10: ='2_Pricing_Engine'!$B$7*('2_Pricing_Engine'!E29/'2_Pricing_Engine'!E18)*(1+'2_Pricing_Engine'!$B$8)^(-11) -> 4.5240437e+08 | E10: ='2_Pricing_Engine'!$B$37*('2_Pricing_Engine'!$B$32-SUM('2_Pricing_Engine'!H15:H18))/'2_Pricing_Engine'!E18 -> -1.2904645e+08 | F10: =((F9+'2_Pricing_Engine'!$B$37)*1.05-800000000*'1_Mortality_Table'!B13)/'1_Mortality_Table'!C13 -> 1.5863383e+08 | G10: =F10/'2_Pricing_Engine'!$B$7 -> 0.19829229
A11: 5 | B11: ='2_Pricing_Engine'!$B$5+5 -> 35 | C11: ='2_Pricing_Engine'!E19 -> 0.9906154 | D11: ='2_Pricing_Engine'!$B$7*('2_Pricing_Engine'!E29/'2_Pricing_Engine'!E19)*(1+'2_Pricing_Engine'!$B$8)^(-10) -> 4.7600039e+08 | E11: ='2_Pricing_Engine'!$B$37*('2_Pricing_Engine'!$B$32-SUM('2_Pricing_Engine'!H15:H19))/'2_Pricing_Engine'!E19 -> -1.5774165e+08 | F11: =((F10+'2_Pricing_Engine'!$B$37)*1.05-800000000*'1_Mortality_Table'!B14)/'1_Mortality_Table'!C14 -> 2.0344164e+08 | G11: =F11/'2_Pricing_Engine'!$B$7 -> 0.25430205
A12: 6 | B12: ='2_Pricing_Engine'!$B$5+6 -> 36 | C12: ='2_Pricing_Engine'!E20 -> 0.98846576 | D12: ='2_Pricing_Engine'!$B$7*('2_Pricing_Engine'!E29/'2_Pricing_Engine'!E20)*(1+'2_Pricing_Engine'!$B$8)^(-9) -> 5.0088733e+08 | E12: ='2_Pricing_Engine'!$B$37*('2_Pricing_Engine'!$B$32-SUM('2_Pricing_Engine'!H15:H20))/'2_Pricing_Engine'!E20 -> -1.8516098e+08 | F12: =((F11+'2_Pricing_Engine'!$B$37)*1.05-800000000*'1_Mortality_Table'!B15)/'1_Mortality_Table'!C15 -> 2.5052042e+08 | G12: =F12/'2_Pricing_Engine'!$B$7 -> 0.31315052
A13: 7 | B13: ='2_Pricing_Engine'!$B$5+7 -> 37 | C13: ='2_Pricing_Engine'!E21 -> 0.98617252 | D13: ='2_Pricing_Engine'!$B$7*('2_Pricing_Engine'!E29/'2_Pricing_Engine'!E21)*(1+'2_Pricing_Engine'!$B$8)^(-8) -> 5.271547e+08 | E13: ='2_Pricing_Engine'!$B$37*('2_Pricing_Engine'!$B$32-SUM('2_Pricing_Engine'!H15:H21))/'2_Pricing_Engine'!E21 -> -2.113785e+08 | F13: =((F12+'2_Pricing_Engine'!$B$37)*1.05-800000000*'1_Mortality_Table'!B16)/'1_Mortality_Table'!C16 -> 2.9998547e+08 | G13: =F13/'2_Pricing_Engine'!$B$7 -> 0.37498183
A14: 8 | B14: ='2_Pricing_Engine'!$B$5+8 -> 38 | C14: ='2_Pricing_Engine'!E22 -> 0.98371695 | D14: ='2_Pricing_Engine'!$B$7*('2_Pricing_Engine'!E29/'2_Pricing_Engine'!E22)*(1+'2_Pricing_Engine'!$B$8)^(-7) -> 5.5489412e+08 | E14: ='2_Pricing_Engine'!$B$37*('2_Pricing_Engine'!$B$32-SUM('2_Pricing_Engine'!H15:H22))/'2_Pricing_Engine'!E22 -> -2.3646515e+08 | F14: =((F13+'2_Pricing_Engine'!$B$37)*1.05-800000000*'1_Mortality_Table'!B17)/'1_Mortality_Table'!C17 -> 3.5196821e+08 | G14: =F14/'2_Pricing_Engine'!$B$7 -> 0.43996026
A15: 9 | B15: ='2_Pricing_Engine'!$B$5+9 -> 39 | C15: ='2_Pricing_Engine'!E23 -> 0.98108059 | D15: ='2_Pricing_Engine'!$B$7*('2_Pricing_Engine'!E29/'2_Pricing_Engine'!E23)*(1+'2_Pricing_Engine'!$B$8)^(-6) -> 5.8420449e+08 | E15: ='2_Pricing_Engine'!$B$37*('2_Pricing_Engine'!$B$32-SUM('2_Pricing_Engine'!H15:H23))/'2_Pricing_Engine'!E23 -> -2.604901e+08 | F15: =((F14+'2_Pricing_Engine'!$B$37)*1.05-800000000*'1_Mortality_Table'!B18)/'1_Mortality_Table'!C18 -> 4.066114e+08 | G15: =F15/'2_Pricing_Engine'!$B$7 -> 0.50826425
A16: 10 | B16: ='2_Pricing_Engine'!$B$5+10 -> 40 | C16: ='2_Pricing_Engine'!E24 -> 0.97823546 | D16: ='2_Pricing_Engine'!$B$7*('2_Pricing_Engine'!E29/'2_Pricing_Engine'!E24)*(1+'2_Pricing_Engine'!$B$8)^(-5) -> 6.1519879e+08 | E16: ='2_Pricing_Engine'!$B$37*('2_Pricing_Engine'!$B$32-SUM('2_Pricing_Engine'!H15:H24))/'2_Pricing_Engine'!E24 -> -2.8352345e+08 | F16: =((F15+'2_Pricing_Engine'!$B$37)*1.05-800000000*'1_Mortality_Table'!B19)/'1_Mortality_Table'!C19 -> 4.6406683e+08 | G16: =F16/'2_Pricing_Engine'!$B$7 -> 0.58008353
A17: 11 | B17: ='2_Pricing_Engine'!$B$5+11 -> 41 | C17: ='2_Pricing_Engine'!E25 -> 0.97515402 | D17: ='2_Pricing_Engine'!$B$7*('2_Pricing_Engine'!E29/'2_Pricing_Engine'!E25)*(1+'2_Pricing_Engine'!$B$8)^(-4) -> 6.4799993e+08 | E17: ='2_Pricing_Engine'!$B$37*('2_Pricing_Engine'!$B$32-SUM('2_Pricing_Engine'!H15:H25))/'2_Pricing_Engine'!E25 -> -3.0563435e+08 | F17: =((F16+'2_Pricing_Engine'!$B$37)*1.05-800000000*'1_Mortality_Table'!B20)/'1_Mortality_Table'!C20 -> 5.2450141e+08 | G17: =F17/'2_Pricing_Engine'!$B$7 -> 0.65562676
A18: 12 | B18: ='2_Pricing_Engine'!$B$5+12 -> 42 | C18: ='2_Pricing_Engine'!E26 -> 0.97181899 | D18: ='2_Pricing_Engine'!$B$7*('2_Pricing_Engine'!E29/'2_Pricing_Engine'!E26)*(1+'2_Pricing_Engine'!$B$8)^(-3) -> 6.8273488e+08 | E18: ='2_Pricing_Engine'!$B$37*('2_Pricing_Engine'!$B$32-SUM('2_Pricing_Engine'!H15:H26))/'2_Pricing_Engine'!E26 -> -3.2688796e+08 | F18: =((F17+'2_Pricing_Engine'!$B$37)*1.05-800000000*'1_Mortality_Table'!B21)/'1_Mortality_Table'!C21 -> 5.8810085e+08 | G18: =F18/'2_Pricing_Engine'!$B$7 -> 0.73512606
A19: 13 | B19: ='2_Pricing_Engine'!$B$5+13 -> 43 | C19: ='2_Pricing_Engine'!E27 -> 0.96821354 | D19: ='2_Pricing_Engine'!$B$7*('2_Pricing_Engine'!E29/'2_Pricing_Engine'!E27)*(1+'2_Pricing_Engine'!$B$8)^(-2) -> 7.1954112e+08 | E19: ='2_Pricing_Engine'!$B$37*('2_Pricing_Engine'!$B$32-SUM('2_Pricing_Engine'!H15:H27))/'2_Pricing_Engine'!E27 -> -3.4734784e+08 | F19: =((F18+'2_Pricing_Engine'!$B$37)*1.05-800000000*'1_Mortality_Table'!B22)/'1_Mortality_Table'!C22 -> 6.5506726e+08 | G19: =F19/'2_Pricing_Engine'!$B$7 -> 0.81883407
A20: 14 | B20: ='2_Pricing_Engine'!$B$5+14 -> 44 | C20: ='2_Pricing_Engine'!E28 -> 0.96431164 | D20: ='2_Pricing_Engine'!$B$7*('2_Pricing_Engine'!E29/'2_Pricing_Engine'!E28)*(1+'2_Pricing_Engine'!$B$8)^(-1) -> 7.5857524e+08 | E20: ='2_Pricing_Engine'!$B$37*('2_Pricing_Engine'!$B$32-SUM('2_Pricing_Engine'!H15:H28))/'2_Pricing_Engine'!E28 -> -3.6707962e+08 | F20: =((F19+'2_Pricing_Engine'!$B$37)*1.05-800000000*'1_Mortality_Table'!B23)/'1_Mortality_Table'!C23 -> 7.2561993e+08 | G20: =F20/'2_Pricing_Engine'!$B$7 -> 0.90702492
A21: 15 | B21: ='2_Pricing_Engine'!$B$5+15 -> 45 | C21: ='2_Pricing_Engine'!E29 -> 0.9600976 | D21: ='2_Pricing_Engine'!$B$7*('2_Pricing_Engine'!E29/'2_Pricing_Engine'!E29)*(1+'2_Pricing_Engine'!$B$8)^(0) -> 800000000 | E21: ='2_Pricing_Engine'!$B$37*('2_Pricing_Engine'!$B$32-SUM('2_Pricing_Engine'!H15:H29))/'2_Pricing_Engine'!E29 -> -3.8614442e+08 | F21: =((F20+'2_Pricing_Engine'!$B$37)*1.05-800000000*'1_Mortality_Table'!B24)/'1_Mortality_Table'!C24 -> 7.9999999e+08 | G21: =F21/'2_Pricing_Engine'!$B$7 -> 0.99999999
A24: [ (Reserve at t-1 + Current Premium) invested at 5% - Expected Death Claims ] / Expected Survivors

Sheet 4_Stress_Testing
A1: STRESS TESTING — NAP SENSITIVITY ANALYSIS
A2: Objective: Measure the sensitivity of Premium to Interest Rate and Bancassurance Lapse shocks.
A4: SCENARIO A — NAP vs Interest Rate (mortality = base CSO 1980)
A5: Interest Rate (i) | B5: Gross Premium (VND/year) | C5: vs Base (5%) | D5: Premium Burden (income 300M)
A6: 0.03 | B6: 45699020 | C6: HIGH
A7: 0.04 | B7: 42336140 | C7: MOD
A8: 0.05 | B8: 39200560 | C8: BASE
A11: SCENARIO B — Combined Stress: Interest × Bancassurance Lapse
A12: Scenario | B12: Interest Rate | C12: Commission Yr1 | D12: Lapse Yr1 | E12: Gross Premium | F12: Business Impact
A13: Base Case | B13: 5.0% | C13: 0.8 | D13: 0 | E13: 39200560 | F13: Baseline pricing. Profit margin is stable under standard assumptions.
A14: Banca Crisis | B14: 0.05 | C14: 0.8 | D14: 0.25 | E14: 39313590 | F14: Negligible premium impact (+0.3%). Liability release mathematically hedges the 80% upfront commission loss.
A15: Adverse 1 | B15: 0.04 | C15: 0.8 | D15: 0.25 | E15: 41671770 | F15: Premium increases by 6.3% due to yield compression. Profitability becomes highly sensitive to lapse.
A16: Worst Case | B16: 3.0% | C16: 0.8 | D16: 0.25 | E16: 44212590 | F16: Severe premium surge (+12.8%). Product becomes commercially unviable without redesigning the commission structure.
A19: KEY FINDINGS & ACTUARIAL RECOMMENDATION
A20: 1. Python DCF Calibration: Excel's commutation rounding errors (Actuarial Drift) were identified and eliminated by calibrating the Base NAP via a Python Discounted Cash Flow model.
A21: 2. Interest Rate Risk: The product is highly sensitive to interest rate drops; a 200bps decrease (from 5% to 3%) forces a ~18% increase in Pure Premium.
A22: 3. Bancassurance Crisis Impact: An upfront commission structure (80% Yr-1) combined with severe early surrender (25% Yr-1) creates heavy acquisition losses.
A23: 4. The "Liability Release" Effect: Surprisingly, in this 15-year Endowment, early lapses mathematically offset commission losses because the insurer is released from the massive 800M maturity obligation.
